{
  "name": "Acmemarkets",
  "stores": [
    {
      "address": "160 W Putnam Ave, Greenwich, CT 06830",
      "phone": "203-622-2944",
      "id": "2036222944"
    },
    {
      "address": "288 Elm St, New Canaan, CT 06840",
      "phone": "203-966-0017",
      "id": "2039660017"
    },
    {
      "address": "1261 E Putnam Ave, Riverside, CT 06878",
      "phone": "203-637-0188",
      "id": "2036370188"
    },
    {
      "address": "1201 High Ridge Rd, Stamford, CT 06905",
      "phone": "203-321-0429",
      "id": "2033210429"
    },
    {
      "address": "146 Fox Hunt Dr, Bear, DE 19701",
      "phone": "302-836-9380",
      "id": "3028369380"
    },
    {
      "address": "128 Lantana Dr, Hockessin, DE 19707",
      "phone": "302-234-9000",
      "id": "3022349000"
    },
    {
      "address": "460 E Main St, Middletown, DE 19709",
      "phone": "302-449-1870",
      "id": "3024491870"
    },
    {
      "address": "1 University Plaza, Newark, DE 19702",
      "phone": "302-738-9509",
      "id": "3027389509"
    },
    {
      "address": "100 College Square, Newark, DE 19711",
      "phone": "302-286-0425",
      "id": "3022860425"
    },
    {
      "address": "100 Suburban Dr, Newark, DE 19711",
      "phone": "302-453-2330",
      "id": "3024532330"
    },
    {
      "address": "18578 Coastal Hwy Unit 13, Rehoboth Beach, DE 19971",
      "phone": "302-644-1255",
      "id": "3026441255"
    },
    {
      "address": "236 E Glenwood Ave, Smyrna, DE 19977",
      "phone": "302-653-9600",
      "id": "3026539600"
    },
    {
      "address": "1308 Centerville Rd, Wilmington, DE 19808",
      "phone": "302-994-3660",
      "id": "3029943660"
    },
    {
      "address": "1401 N Dupont St, Wilmington, DE 19806",
      "phone": "302-658-0575",
      "id": "3026580575"
    },
    {
      "address": "1812 Marsh Rd, Wilmington, DE 19810",
      "phone": "302-529-8520",
      "id": "3025298520"
    },
    {
      "address": "1901 Concord Pike, Wilmington, DE 19803",
      "phone": "302-654-1803",
      "id": "3026541803"
    },
    {
      "address": "2098 Naamans Rd, Wilmington, DE 19810",
      "phone": "302-475-4618",
      "id": "3024754618"
    },
    {
      "address": "4365 Robert Kirkwood Hwy, Wilmington, DE 19808",
      "phone": "302-636-1140",
      "id": "3026361140"
    },
    {
      "address": "4720 Limestone Rd, Wilmington, DE 19808",
      "phone": "302-998-4465",
      "id": "3029984465"
    },
    {
      "address": "611 Railroad Ave, Centreville, MD 21617",
      "phone": "443-262-9150",
      "id": "4432629150"
    },
    {
      "address": "711 Washington Ave, Unit #14, Chestertown, MD 21620",
      "phone": "410-778-5641",
      "id": "4107785641"
    },
    {
      "address": "210 W Marlboro Ave, Easton, MD 21601",
      "phone": "410-822-7073",
      "id": "4108227073"
    },
    {
      "address": "101 Big Elk Mall, Elkton, MD 21921",
      "phone": "410-398-4925",
      "id": "4103984925"
    },
    {
      "address": "9507 Coastal Hwy, Ocean City, MD 21842",
      "phone": "410-723-7004",
      "id": "4107237004"
    },
    {
      "address": "751 S Salisbury Blvd, Salisbury, MD 21801",
      "phone": "410-742-1343",
      "id": "4107421343"
    },
    {
      "address": "45 De Mercurio Dr, Allendale, NJ 07401",
      "phone": "201-934-3350",
      "id": "2019343350"
    },
    {
      "address": "100 E Black Horse Pike, Audubon, NJ 08106",
      "phone": "856-547-3938",
      "id": "8565473938"
    },
    {
      "address": "912 W Bay Ave, Barnegat, NJ 08005",
      "phone": "609-607-5909",
      "id": "6096075909"
    },
    {
      "address": "152 Route 94, Blairstown, NJ 07825",
      "phone": "908-362-1790",
      "id": "9083621790"
    },
    {
      "address": "550 Myrtle Ave, Boonton, NJ 07005",
      "phone": "973-402-4333",
      "id": "9734024333"
    },
    {
      "address": "260 Dunns Mills Rd, Bordentown, NJ 08505",
      "phone": "609-298-2014",
      "id": "6092982014"
    },
    {
      "address": "4236 Harbor Beach Blvd, Brigantine, NJ 08203",
      "phone": "609-264-0041",
      "id": "6092640041"
    },
    {
      "address": "18 Broadway, Browns Mills, NJ 08015",
      "phone": "609-735-1605",
      "id": "6097351605"
    },
    {
      "address": "315 Ocean St, Cape May, NJ 08204",
      "phone": "609-884-7217",
      "id": "6098847217"
    },
    {
      "address": "11 Court House South Dennis Rd, Cape May Court House, NJ 08210",
      "phone": "609-463-9106",
      "id": "6094639106"
    },
    {
      "address": "15 Avalon Blvd, Cape May Court House, NJ 08210",
      "phone": "609-463-1995",
      "id": "6094631995"
    },
    {
      "address": "1060 Raritan Rd, Clark, NJ 07066",
      "phone": "732-340-0056",
      "id": "7323400056"
    },
    {
      "address": "20 S Delsea Dr, Clayton, NJ 08312",
      "phone": "856-881-9884",
      "id": "8568819884"
    },
    {
      "address": "123 E Main St, Denville, NJ 07834",
      "phone": "973-586-2215",
      "id": "9735862215"
    },
    {
      "address": "481 River Rd, Edgewater, NJ 07020",
      "phone": "201-840-8006",
      "id": "2018408006"
    },
    {
      "address": "576 River Rd, Fair Haven, NJ 07704",
      "phone": "732-530-7481",
      "id": "7325307481"
    },
    {
      "address": "2160 Lemoine Ave, Fort Lee, NJ 07024",
      "phone": "201-944-1145",
      "id": "2019441145"
    },
    {
      "address": "3241 US Hwy 9, Freehold, NJ 07728",
      "phone": "732-863-6501",
      "id": "7328636501"
    },
    {
      "address": "40 Ellis St, Haddonfield, NJ 08033",
      "phone": "856-429-0177",
      "id": "8564290177"
    },
    {
      "address": "614 Clinton St, Hoboken, NJ 07030",
      "phone": "201-795-5005",
      "id": "2017955005"
    },
    {
      "address": "125 18th St, Jersey City, NJ 07310",
      "phone": "201-418-0580",
      "id": "2014180580"
    },
    {
      "address": "321 Route 440, Jersey City, NJ 07305",
      "phone": "201-946-2525",
      "id": "2019462525"
    },
    {
      "address": "801 Kenilworth Blvd, Kenilworth, NJ 07033",
      "phone": "908-259-0725",
      "id": "9082590725"
    },
    {
      "address": "616 Newman Springs Rd, Lincroft, NJ 07738",
      "phone": "732-936-0668",
      "id": "7329360668"
    },
    {
      "address": "507 Prospect Ave, Little Silver, NJ 07739",
      "phone": "732-345-9910",
      "id": "7323459910"
    },
    {
      "address": "9600 Long Beach Blvd, Long Beach Township, NJ 08008",
      "phone": "609-492-0510",
      "id": "6094920510"
    },
    {
      "address": "125 Franklin Turnpike, Mahwah, NJ 07430",
      "phone": "201-529-9775",
      "id": "2015299775"
    },
    {
      "address": "609 E Bay Ave, Manahawkin, NJ 08050",
      "phone": "609-597-4009",
      "id": "6095974009"
    },
    {
      "address": "176 E Main St, Manasquan, NJ 08736",
      "phone": "732-223-9622",
      "id": "7322239622"
    },
    {
      "address": "300 S Lenola Rd, Maple Shade, NJ 08052",
      "phone": "856-778-2028",
      "id": "8567782028"
    },
    {
      "address": "41 W Main St, Maple Shade, NJ 08052",
      "phone": "856-779-9891",
      "id": "8567799891"
    },
    {
      "address": "4454 Black Horse Pike, Mays Landing, NJ 08330",
      "phone": "609-625-4710",
      "id": "6096254710"
    },
    {
      "address": "175 Route 70, Medford, NJ 08055",
      "phone": "609-953-0006",
      "id": "6099530006"
    },
    {
      "address": "125 Bound Brook Rd, Middlesex, NJ 08846",
      "phone": "732-968-9136",
      "id": "7329689136"
    },
    {
      "address": "136 Lake St, Midland Park, NJ 07432",
      "phone": "201-493-7050",
      "id": "2014937050"
    },
    {
      "address": "300 Ryders Ln, Milltown, NJ 08850",
      "phone": "732-254-7900",
      "id": "7322547900"
    },
    {
      "address": "510 Valley Rd, Montclair, NJ 07043",
      "phone": "973-746-0058",
      "id": "9737460058"
    },
    {
      "address": "329 Speedwell Ave, Morris Plains, NJ 07950",
      "phone": "973-984-9445",
      "id": "9739849445"
    },
    {
      "address": "531 High St, Mount Holly, NJ 08060",
      "phone": "609-702-1776",
      "id": "6097021776"
    },
    {
      "address": "1260 Springfield Ave, New Providence, NJ 07974",
      "phone": "908-286-1725",
      "id": "9082861725"
    },
    {
      "address": "3845 Bayshore Rd, North Cape May, NJ 08204",
      "phone": "609-884-1203",
      "id": "6098841203"
    },
    {
      "address": "2400 Delaware Ave, North Wildwood, NJ 08260",
      "phone": "609-846-9010",
      "id": "6098469010"
    },
    {
      "address": "5774 Berkshire Valley Rd, Oak Ridge, NJ 07438",
      "phone": "973-697-3005",
      "id": "9736973005"
    },
    {
      "address": "3428 Simpson Ave, Ocean City, NJ 08226",
      "phone": "609-525-2160",
      "id": "6095252160"
    },
    {
      "address": "800 West Ave, Ocean City, NJ 08226",
      "phone": "609-814-9780",
      "id": "6098149780"
    },
    {
      "address": "2087 Shore Rd, Ocean View, NJ 08230",
      "phone": "609-624-9004",
      "id": "6096249004"
    },
    {
      "address": "3500 Route 9, Old Bridge, NJ 08857",
      "phone": "732-607-9275",
      "id": "7326079275"
    },
    {
      "address": "251 N Broadway, Pennsville, NJ 08070",
      "phone": "856-678-4213",
      "id": "8566784213"
    },
    {
      "address": "690 Millbrook Ave, Randolph, NJ 07869",
      "phone": "973-895-2699",
      "id": "9738952699"
    },
    {
      "address": "501 E Evesham Rd, Runnemede, NJ 08078",
      "phone": "856-939-5403",
      "id": "8569395403"
    },
    {
      "address": "75 Mayhill St, Saddle Brook, NJ 07663",
      "phone": "201-712-1130",
      "id": "2017121130"
    },
    {
      "address": "6212 Landis Ave, Sea Isle City, NJ 08243",
      "phone": "609-263-1510",
      "id": "6092631510"
    },
    {
      "address": "5 Ortley Plaza, Seaside Heights, NJ 08751",
      "phone": "732-830-0880",
      "id": "7328300880"
    },
    {
      "address": "415 Egg Harbor Rd, Sewell, NJ 08080",
      "phone": "856-256-8852",
      "id": "8562568852"
    },
    {
      "address": "515 Berlin-Cross Keys Rd, Sicklerville, NJ 08081",
      "phone": "856-728-3674",
      "id": "8567283674"
    },
    {
      "address": "212 New Rd, Somers Point, NJ 08244",
      "phone": "609-653-6853",
      "id": "6096536853"
    },
    {
      "address": "455 Route 23 N, Sussex, NJ 07461",
      "phone": "973-702-4020",
      "id": "9737024020"
    },
    {
      "address": "1619 Center Square Rd, Swedesboro, NJ 08085",
      "phone": "856-467-8936",
      "id": "8564678936"
    },
    {
      "address": "4400 S Broad St, Trenton, NJ 08620",
      "phone": "609-888-9898",
      "id": "6098889898"
    },
    {
      "address": "953 Route 33, Trenton, NJ 08690",
      "phone": "609-890-2551",
      "id": "6098902551"
    },
    {
      "address": "425 US Hwy 9, Tuckerton, NJ 08087",
      "phone": "609-296-9303",
      "id": "6092969303"
    },
    {
      "address": "5100 Wellington Ave, Ventnor City, NJ 08406",
      "phone": "609-823-0020",
      "id": "6098230020"
    },
    {
      "address": "530 Rt 515 Unit 1, Vernon, NJ 07462",
      "phone": "973-764-5350",
      "id": "9737645350"
    },
    {
      "address": "301 S Main St, Vineland, NJ 08360",
      "phone": "856-507-1101",
      "id": "8565071101"
    },
    {
      "address": "700 Haddonfield-Berlin Rd, Voorhees, NJ 08043",
      "phone": "856-782-1122",
      "id": "8567821122"
    },
    {
      "address": "2007 Route 35, Wall Township, NJ 07719",
      "phone": "732-282-1630",
      "id": "7322821630"
    },
    {
      "address": "177 Washington Valley Rd, Warren, NJ 07059",
      "phone": "732-764-3800",
      "id": "7327643800"
    },
    {
      "address": "19-21 Ave At Port Imperial, West New York, NJ 07093",
      "phone": "201-553-1030",
      "id": "2015531030"
    },
    {
      "address": "400 W Cuthbert Blvd, Westmont, NJ 08108",
      "phone": "856-858-2226",
      "id": "8568582226"
    },
    {
      "address": "5300 Park Blvd, Wildwood, NJ 08260",
      "phone": "609-522-7165",
      "id": "6095227165"
    },
    {
      "address": "23 Levitt Pkwy, Willingboro, NJ 08046",
      "phone": "609-871-0670",
      "id": "6098710670"
    },
    {
      "address": "631 Mantua Pike, Woodbury, NJ 08096",
      "phone": "856-848-0224",
      "id": "8568480224"
    },
    {
      "address": "857 Route 45, Woodstown, NJ 08098",
      "phone": "856-769-8000",
      "id": "8567698000"
    },
    {
      "address": "1511 NY Route 22, Brewster, NY 10509",
      "phone": "845-940-0575",
      "id": "8459400575"
    },
    {
      "address": "1886 Pleasantville Rd, Briarcliff Manor, NY 10510",
      "phone": "914-945-7225",
      "id": "9149457225"
    },
    {
      "address": "12 Cedar St, Bronxville, NY 10708",
      "phone": "914-793-1001",
      "id": "9147931001"
    },
    {
      "address": "100 Route 22, Goldens Bridge, NY 10526",
      "phone": "914-232-7610",
      "id": "9142327610"
    },
    {
      "address": "829 Route 82, Hopewell Junction, NY 12533",
      "phone": "845-227-0581",
      "id": "8452270581"
    },
    {
      "address": "272 US Route 6, Mahopac, NY 10541",
      "phone": "845-621-5110",
      "id": "8456215110"
    },
    {
      "address": "3071 E Main St, Mohegan Lake, NY 10547",
      "phone": "914-526-6688",
      "id": "9145266688"
    },
    {
      "address": "23 Quaker Ridge Rd, New Rochelle, NY 10804",
      "phone": "914-636-2133",
      "id": "9146362133"
    },
    {
      "address": "3101 Route 22, Patterson, NY 12563",
      "phone": "845-878-2044",
      "id": "8458782044"
    },
    {
      "address": "13 North Ave, Pleasant Valley, NY 12569",
      "phone": "845-635-4420",
      "id": "8456354420"
    },
    {
      "address": "261 S Ridge St, Rye Brook, NY 10573",
      "phone": "914-937-2233",
      "id": "9149372233"
    },
    {
      "address": "1366 E Main St, Shrub Oak, NY 10588",
      "phone": "914-528-3620",
      "id": "9145283620"
    },
    {
      "address": "610 Columbus Ave, Thornwood, NY 10594",
      "phone": "914-747-0455",
      "id": "9147470455"
    },
    {
      "address": "103 Knollwood Rd, White Plains, NY 10607",
      "phone": "914-682-1711",
      "id": "9146821711"
    },
    {
      "address": "660 McLean Ave, Yonkers, NY 10704",
      "phone": "914-376-8755",
      "id": "9143768755"
    },
    {
      "address": "100 Triangle Center, Yorktown Heights, NY 10598",
      "phone": "914-455-3810",
      "id": "9144553810"
    },
    {
      "address": "851 Gap Newport Pike, Avondale, PA 19311",
      "phone": "610-268-3898",
      "id": "6102683898"
    },
    {
      "address": "121 E City Ave, Bala Cynwyd, PA 19004",
      "phone": "610-667-7021",
      "id": "6106677021"
    },
    {
      "address": "1336 Bristol Pike Suite 100, Bensalem, PA 19020",
      "phone": "215-638-8190",
      "id": "2156388190"
    },
    {
      "address": "2301 Bristol Rd, Bensalem, PA 19020",
      "phone": "215-757-9995",
      "id": "2157579995"
    },
    {
      "address": "643 Conchester Pike, Boothwyn, PA 19061",
      "phone": "610-859-0001",
      "id": "6108590001"
    },
    {
      "address": "567 N Sproul Rd, Broomall, PA 19008",
      "phone": "610-325-2880",
      "id": "6103252880"
    },
    {
      "address": "601 W Lancaster Ave, Bryn Mawr, PA 19010",
      "phone": "610-525-1950",
      "id": "6105251950"
    },
    {
      "address": "400 Simpson Dr, Chester Springs, PA 19425",
      "phone": "610-458-7004",
      "id": "6104587004"
    },
    {
      "address": "5300 Baltimore Pike, Clifton Heights, PA 19018",
      "phone": "610-284-6800",
      "id": "6102846800"
    },
    {
      "address": "3951 Lincoln Hwy, Downingtown, PA 19335",
      "phone": "610-873-8315",
      "id": "6108738315"
    },
    {
      "address": "480 N Main St, Doylestown, PA 18901",
      "phone": "215-340-1341",
      "id": "2153401341"
    },
    {
      "address": "1825 Limekiln Pike, Dresher, PA 19025",
      "phone": "215-643-3992",
      "id": "2156433992"
    },
    {
      "address": "105 E Street Rd, Feasterville Trevose, PA 19053",
      "phone": "215-942-4891",
      "id": "2159424891"
    },
    {
      "address": "1640 Bethlehem Pike, Flourtown, PA 19031",
      "phone": "215-836-2560",
      "id": "2158362560"
    },
    {
      "address": "124 Morton Ave, Folsom, PA 19033",
      "phone": "610-237-3800",
      "id": "6102373800"
    },
    {
      "address": "101 Byers Dr, Glen Mills, PA 19342",
      "phone": "610-459-2759",
      "id": "6104592759"
    },
    {
      "address": "1305 W Chester Pike, Havertown, PA 19083",
      "phone": "610-446-1191",
      "id": "6104461191"
    },
    {
      "address": "503 S MacDade Blvd, Holmes, PA 19043",
      "phone": "610-586-0557",
      "id": "6105860557"
    },
    {
      "address": "200 Blair Mill Rd, Horsham, PA 19044",
      "phone": "215-956-1600",
      "id": "2159561600"
    },
    {
      "address": "323 Old York Rd, Jenkintown, PA 19046",
      "phone": "215-886-2911",
      "id": "2158862911"
    },
    {
      "address": "6800 New Falls Rd, Levittown, PA 19057",
      "phone": "215-946-1840",
      "id": "2159461840"
    },
    {
      "address": "1095 W Baltimore Pike, Media, PA 19063",
      "phone": "610-891-0407",
      "id": "6108910407"
    },
    {
      "address": "527 E Baltimore Pike, Media, PA 19063",
      "phone": "610-565-5072",
      "id": "6105655072"
    },
    {
      "address": "829 Montgomery Ave, Narberth, PA 19072",
      "phone": "610-668-1738",
      "id": "6106681738"
    },
    {
      "address": "48 West Rd, Newtown, PA 18940",
      "phone": "215-504-9585",
      "id": "2155049585"
    },
    {
      "address": "3590 W Chester Pike, Newtown Square, PA 19073",
      "phone": "610-353-8018",
      "id": "6103538018"
    },
    {
      "address": "2761 W Ridge Pike, Norristown, PA 19403",
      "phone": "610-630-0890",
      "id": "6106300890"
    },
    {
      "address": "39 Leopard Rd, Paoli, PA 19301",
      "phone": "610-240-0101",
      "id": "6102400101"
    },
    {
      "address": "1001 South St, Philadelphia, PA 19147",
      "phone": "215-238-1108",
      "id": "2152381108"
    },
    {
      "address": "1400 E Passyunk Ave, Philadelphia, PA 19147",
      "phone": "215-467-2221",
      "id": "2154672221"
    },
    {
      "address": "180 W Girard Ave, Philadelphia, PA 19123",
      "phone": "215-574-2922",
      "id": "2155742922"
    },
    {
      "address": "1901 Johnston St, Philadelphia, PA 19145",
      "phone": "215-336-4441",
      "id": "2153364441"
    },
    {
      "address": "2101-41 Cottman Ave, Philadelphia, PA 19149",
      "phone": "215-728-1010",
      "id": "2157281010"
    },
    {
      "address": "29 Snyder Ave, Philadelphia, PA 19148",
      "phone": "215-271-5603",
      "id": "2152715603"
    },
    {
      "address": "309 S 5th St, Philadelphia, PA 19106",
      "phone": "215-413-9725",
      "id": "2154139725"
    },
    {
      "address": "3200-09 Red Lion Rd, Philadelphia, PA 19114",
      "phone": "215-637-4620",
      "id": "2156374620"
    },
    {
      "address": "4001 Walnut St, Philadelphia, PA 19104",
      "phone": "445-888-3634",
      "id": "4458883634"
    },
    {
      "address": "5927-59 Ridge Ave, Philadelphia, PA 19128",
      "phone": "215-487-7180",
      "id": "2154877180"
    },
    {
      "address": "6601 Roosevelt Blvd, Philadelphia, PA 19149",
      "phone": "215-338-4700",
      "id": "2153384700"
    },
    {
      "address": "6640 Oxford Ave, Philadelphia, PA 19111",
      "phone": "215-725-9310",
      "id": "2157259310"
    },
    {
      "address": "701 Cathedral Rd Suit 34, Philadelphia, PA 19128",
      "phone": "215-483-7766",
      "id": "2154837766"
    },
    {
      "address": "7010 Germantown Ave, Philadelphia, PA 19119",
      "phone": "215-247-1160",
      "id": "2152471160"
    },
    {
      "address": "7700 Crittenden St, Philadelphia, PA 19118",
      "phone": "215-248-6490",
      "id": "2152486490"
    },
    {
      "address": "8200 Roosevelt Blvd, Philadelphia, PA 19152",
      "phone": "215-338-8077",
      "id": "2153388077"
    },
    {
      "address": "920 Red Lion Rd, Philadelphia, PA 19115",
      "phone": "215-676-5601",
      "id": "2156765601"
    },
    {
      "address": "785 Starr St, Phoenixville, PA 19460",
      "phone": "610-933-6299",
      "id": "6109336299"
    },
    {
      "address": "800 2nd St Pike, Richboro, PA 18954",
      "phone": "215-354-4424",
      "id": "2153544424"
    },
    {
      "address": "815 Lansdowne Ave, Upper Darby, PA 19082",
      "phone": "610-789-0898",
      "id": "6107890898"
    },
    {
      "address": "700 W Lancaster Ave, Wayne, PA 19087",
      "phone": "610-341-6073",
      "id": "6103416073"
    },
    {
      "address": "907 Paoli Pike, West Chester, PA 19380",
      "phone": "610-431-4726",
      "id": "6104314726"
    }
  ]
}